kfda/__init__.py
kfda/kfda.py
kfda/mnist.py
kfda-0.1.1.dist-info/LICENSE
kfda-0.1.1.dist-info/METADATA
kfda-0.1.1.dist-info/WHEEL
kfda-0.1.1.dist-info/top_level.txt
kfda-0.1.1.dist-info/RECORD
