Metadata-Version: 2.1
Name: kfda
Version: 0.1.1
Summary: Kernel FDA implementation described in https://arxiv.org/abs/1906.09436
Home-page: https://github.com/concavegit/kfda
Author: Kawin Nikomborirak
Author-email: concavemail@gmail.com
License: UNKNOWN
Platform: UNKNOWN
Classifier: Programming Language :: Python :: 3
Classifier: License :: OSI Approved :: MIT License
Classifier: Operating System :: OS Independent
Requires-Python: >=3.6
